{
  "headers": {
    "x-amz-cf-pop": "LHR61-C1",
    "x-amz-version-id": "6mFG_JeAIn7qZP7t4VkfKSODDc_0nmxs",
    "cache-control": "public, max-age=31536000, immutable",
    "via": "1.1 0fe4e9874d2e0d61c17aa980fd6da8ee.cloudfront.net (CloudFront)",
    "server": "deno/europe-west2-a",
    "content-security-policy": "default-src 'none'; style-src 'unsafe-inline'; sandbox",
    "vary": "Accept-Encoding, Origin",
    "age": "58",
    "access-control-allow-origin": "*",
    "date": "Mon, 19 Sep 2022 13:47:39 GMT",
    "etag": "\"6b1add08765b17094952b4a735dc7c42\"",
    "x-cache": "Hit from cloudfront",
    "accept-ranges": "bytes",
    "content-length": "10360",
    "content-type": "application/typescript; charset=utf-8",
    "last-modified": "Thu, 23 Jun 2022 18:07:07 GMT",
    "x-amz-cf-id": "gmupXboSDPfgOFPQhQ4ZHv1xoGMkScRhjPCqBz-U69GSVbWFfx8E8w==",
    "x-amz-replication-status": "FAILED"
  },
  "url": "https://deno.land/std@0.145.0/testing/bdd.ts",
  "now": {
    "secs_since_epoch": 1663595316,
    "nanos_since_epoch": 809692000
  }
}